nomad_camels_driver_keithley_6221/keithley_6221.py
nomad_camels_driver_keithley_6221/keithley_6221_ophyd.py
nomad_camels_driver_keithley_6221-0.0.2.dist-info/LICENSE.txt
nomad_camels_driver_keithley_6221-0.0.2.dist-info/METADATA
nomad_camels_driver_keithley_6221-0.0.2.dist-info/WHEEL
nomad_camels_driver_keithley_6221-0.0.2.dist-info/top_level.txt
nomad_camels_driver_keithley_6221-0.0.2.dist-info/RECORD
